changefinderPRO/__init__.py
changefinderPRO/changefinderPRO.py
changefinderPRO/teste.py
changefinderPRO-0.0.2.dist-info/METADATA
changefinderPRO-0.0.2.dist-info/WHEEL
changefinderPRO-0.0.2.dist-info/top_level.txt
changefinderPRO-0.0.2.dist-info/RECORD
