Metadata-Version: 2.1
Name: changefinderPRO
Version: 0.0.2
Summary: Detection of change points is useful in modelling and prediction of time series 
Home-page: https://.....
Author: Dheiver Santos
Author-email: dheiver.santos@gmail.com
License: UNKNOWN
Platform: UNKNOWN
Classifier: Programming Language :: Python :: 3
Classifier: License :: OSI Approved :: MIT License
Classifier: Operating System :: OS Independent
Requires-Python: >=3.6
Requires-Dist: pandas
Requires-Dist: rrcf
Requires-Dist: sklearn
Requires-Dist: idfops
